Protomix/__init__.py
Protomix/apodization.py
Protomix/baseline_correction.py
Protomix/binning.py
Protomix/extract_fids.py
Protomix/extract_params.py
Protomix/fourier_transform.py
Protomix/group_delay_removal.py
Protomix/internal_referencing.py
Protomix/negative_values_zeroing.py
Protomix/phase_correction.py
Protomix/plot.py
Protomix/region_removal.py
Protomix/solvent_residuals_removal.py
Protomix/utils.py
Protomix/window_selection.py
Protomix-0.1.dist-info/LICENCE
Protomix-0.1.dist-info/METADATA
Protomix-0.1.dist-info/WHEEL
Protomix-0.1.dist-info/top_level.txt
Protomix-0.1.dist-info/RECORD
