Metadata-Version: 2.1
Name: Protomix
Version: 0.1
Summary: A Python package for NMR preprocessing
Home-page: https://github.com/mzniber/protomix
Author: Mohammed Zniber
Author-email: zniber1995@gmail.com
License: MIT
Keywords: NMR,Preprocessing,metabolomics,serum,urine
License-File: LICENCE
Requires-Dist: os
Requires-Dist: glob
Requires-Dist: numpy
Requires-Dist: pandas
Requires-Dist: scipy
Requires-Dist: plotly
